[{"is_private": "false", "venue_name": "Online event", "rsvp_limit": 0, "fee_currency": "USD", "fee": 0, "venue_lon": 179.1962, "title": "MeetUp Python Alicante", "type": "Meetup", "venue_address1": "", "venue_address2": "", "local_time": "2021-04-22 19:00:00 EDT", "fee_label": "Price", "myRsvp": -1, "ctime": "2020-09-14 03:43:06 EDT", "guest_limit": 0, "rsvp_closed": "false", "confirmCount": 15, "venue_id": 26906060, "venue_zip": "", "chapter_url": "https://www.meetup.com/python_alc/#", "servertime": "2021-04-22 13:00:00 EDT", "venue_city": "", "event_url": "https://www.meetup.com/python_alc/events/277038656/", "allow_maybe_rsvps": "false", "commentCount": 0, "descr": "<p>\u00a1 MeetUp Python Alicante !</p> <p>O lo que es lo mismo, una quedada informal d\u00f3nde hablaremos sobre Python, nuestros proyectos en los que estamos trabajando tanto de forma profesional como por afici\u00f3n.</p> <p>Al ser un evento informal, no hace falta que tengas ning\u00fan conocimiento previo, solo inter\u00e9s por la programaci\u00f3n en general y en Python en particular; as\u00ed que es una buena oportunidad si quieres empezar.</p> <p>\u2022 Qu\u00e9 has de traer<br/>Ganas de participar y hacer comunidad.</p> ", "venue_country": "", "event_id": 277038656, "fee_desc": "per person", "chapter_id": 26484481, "venue_lat": -8.521147, "meetupId": "python_alc"}, {"is_private": "false", "venue_name": "Online event", "rsvp_limit": 0, "fee_currency": "USD", "fee": 0, "venue_lon": 179.1962, "title": "MeetUp Python Alicante", "type": "Meetup", "venue_address1": "", "venue_address2": "", "local_time": "2021-05-27 19:00:00 EDT", "fee_label": "Price", "myRsvp": -1, "ctime": "2020-09-14 03:43:06 EDT", "guest_limit": 0, "rsvp_closed": "false", "confirmCount": 4, "venue_id": 26906060, "venue_zip": "", "chapter_url": "https://www.meetup.com/python_alc/#", "servertime": "2021-05-27 13:00:00 EDT", "venue_city": "", "event_url": "https://www.meetup.com/python_alc/events/277068475/", "allow_maybe_rsvps": "false", "commentCount": 0, "descr": "<p>\u00a1 MeetUp Python Alicante !</p> <p>O lo que es lo mismo, una quedada informal d\u00f3nde hablaremos sobre Python, nuestros proyectos en los que estamos trabajando tanto de forma profesional como por afici\u00f3n.</p> <p>Al ser un evento informal, no hace falta que tengas ning\u00fan conocimiento previo, solo inter\u00e9s por la programaci\u00f3n en general y en Python en particular; as\u00ed que es una buena oportunidad si quieres empezar.</p> <p>\u2022 Qu\u00e9 has de traer<br/>Ganas de participar y hacer comunidad.</p> ", "venue_country": "", "event_id": 277068475, "fee_desc": "per person", "chapter_id": 26484481, "venue_lat": -8.521147, "meetupId": "python_alc"}, {"is_private": "false", "venue_name": "Online event", "rsvp_limit": 0, "fee_currency": "USD", "fee": 0, "venue_lon": 179.1962, "title": "MeetUp Python Alicante", "type": "Meetup", "venue_address1": "", "venue_address2": "", "local_time": "2021-06-24 19:00:00 EDT", "fee_label": "Price", "myRsvp": -1, "ctime": "2020-09-14 03:43:06 EDT", "guest_limit": 0, "rsvp_closed": "false", "confirmCount": 2, "venue_id": 26906060, "venue_zip": "", "chapter_url": "https://www.meetup.com/python_alc/#", "servertime": "2021-06-24 13:00:00 EDT", "venue_city": "", "event_url": "https://www.meetup.com/python_alc/events/277068478/", "allow_maybe_rsvps": "false", "commentCount": 0, "descr": "<p>\u00a1 MeetUp Python Alicante !</p> <p>O lo que es lo mismo, una quedada informal d\u00f3nde hablaremos sobre Python, nuestros proyectos en los que estamos trabajando tanto de forma profesional como por afici\u00f3n.</p> <p>Al ser un evento informal, no hace falta que tengas ning\u00fan conocimiento previo, solo inter\u00e9s por la programaci\u00f3n en general y en Python en particular; as\u00ed que es una buena oportunidad si quieres empezar.</p> <p>\u2022 Qu\u00e9 has de traer<br/>Ganas de participar y hacer comunidad.</p> ", "venue_country": "", "event_id": 277068478, "fee_desc": "per person", "chapter_id": 26484481, "venue_lat": -8.521147, "meetupId": "python_alc"}, {"is_private": "false", "rsvp_limit": 0, "chapter_url": "https://www.meetup.com/python_alc/#", "fee_currency": "USD", "fee": 0, "servertime": "2021-07-22 13:00:00 EDT", "title": "MeetUp Python Alicante", "type": "Meetup", "event_url": "https://www.meetup.com/python_alc/events/jpcqxrycckbdc/", "allow_maybe_rsvps": "false", "commentCount": 0, "descr": "<p>\u00a1 MeetUp Python Alicante !</p> <p>O lo que es lo mismo, una quedada informal d\u00f3nde hablaremos sobre Python, nuestros proyectos en los que estamos trabajando tanto de forma profesional como por afici\u00f3n.</p> <p>Al ser un evento informal, no hace falta que tengas ning\u00fan conocimiento previo, solo inter\u00e9s por la programaci\u00f3n en general y en Python en particular; as\u00ed que es una buena oportunidad si quieres empezar.</p> <p>\u2022 Qu\u00e9 has de traer<br/>Ganas de participar y hacer comunidad.</p> ", "local_time": "2021-07-22 19:00:00 EDT", "fee_label": "Price", "myRsvp": -1, "ctime": "2020-09-14 03:43:06 EDT", "fee_desc": "per person", "guest_limit": 0, "rsvp_closed": "false", "confirmCount": 1, "chapter_id": 26484481, "meetupId": "python_alc"}, {"is_private": "false", "venue_name": "Online event", "rsvp_limit": 0, "fee_currency": "USD", "fee": 0, "venue_lon": 179.1962, "title": "CARTIER-IA platform: a platform for the management of medical data and imaging", "type": "Meetup", "venue_address1": "", "venue_address2": "", "local_time": "2021-04-15 18:00:00 EDT", "fee_label": "", "myRsvp": -1, "ctime": "2021-03-25 03:41:26 EDT", "guest_limit": 0, "rsvp_closed": "false", "confirmCount": 19, "venue_id": 26906060, "venue_zip": "", "chapter_url": "https://www.meetup.com/PyData-Salamanca/#", "servertime": "2021-04-15 12:00:00 EDT", "venue_city": "", "event_url": "https://www.meetup.com/PyData-Salamanca/events/277150732/", "allow_maybe_rsvps": "false", "commentCount": 0, "descr": "<p>PyData Salamanca is proud to announce a new meetup!</p> <p>All the talks will be streamed on our Youtube channel.</p> <p>Youtube Live link: <a href=\"https://youtu.be/475my9vk6Q8\" class=\"embedded\">https://youtu.be/475my9vk6Q8</a></p> <p>AGENDA</p> <p>18:00 pm - Keynote (Spanish)<br/>Title: CARTIER-IA platform: a platform for the management of medical data and imaging.</p> <p>Abstract:<br/>Artificial Intelligence (AI) is growing in popularity due to its support of to complex tasks in different context. Several domains benefit from the application of advanced algorithms and models to their specific problems. One of these domains is the medical sector, where these algorithms can support disease detection, image segmentation and other multiple tasks. However, the intrinsic heterogeneity of medical data makes the application of AI solutions a complex job. In this presentation, we will review the design decisions taken for the implementation of the CARTIER-IA platform: a platform for the management of medical data and imaging with the goal of applying AI algorithms on the unified resources in a straight-forward way.</p> <p>Speaker: Andrea V\u00e1zquez-Ingelmo received the bachelor\u2019s degree in computer engineering from the University of Salamanca, Salamanca, in 2016 and the master\u2019s degree in computer engineering from the same university in 2018. She is a member of the Research Group of Interaction and eLearning (GRIAL), where she is pursuing her PhD degree in computer science. Her area of research is related to human-computer interaction, software engineering, information visualization and machine learning applications.</p> <p>18:45 pm - Q&amp;A<br/>All questions can be asked using the Youtube live chat.<br/>Questions will be addressed at the end of the keynote.</p> <p>--------------------------------------------------------------------------------------------------<br/>What is PyData? PyData is a group for users and developers of data analysis tools to share ideas and learn from each other. We gather to discuss best practices, new approaches, and emerging technologies for data management, processing, analytics, and visualization. We approach data science using many languages, including (but not limited to) Python, Julia, and R.<br/>--------------------------------------------------------------------------------------------------</p> <p>FUTURE SPEAKERS</p> <p>Would you like to speak at this meetup or a future one? Please submit your proposal at coordinaciondatalabgmailcom</p> ", "venue_country": "", "event_id": 277150732, "fee_desc": "", "chapter_id": 30890235, "venue_lat": -8.521147, "meetupId": "PyData-Salamanca"}, {"is_private": "false", "venue_name": "Online event", "rsvp_limit": 0, "fee_currency": "USD", "fee": 0, "venue_lon": 179.1962, "title": "La culebrilla que se muerde la cola - Recursividad en Python", "type": "Meetup", "venue_address1": "", "venue_address2": "", "local_time": "2021-04-29 18:00:00 EDT", "fee_label": "", "myRsvp": -1, "ctime": "2021-04-19 09:19:26 EDT", "guest_limit": 0, "rsvp_closed": "false", "confirmCount": 151, "venue_id": 26906060, "venue_zip": "", "chapter_url": "https://www.meetup.com/python-madrid/#", "servertime": "2021-04-29 12:00:00 EDT", "venue_city": "", "event_url": "https://www.meetup.com/python-madrid/events/277663457/", "allow_maybe_rsvps": "false", "commentCount": 0, "descr": "<p>Cuando Python Madrid me pregunt\u00f3 si quer\u00eda dar una charla, yo propuse hacerla sobre Tail Call Optimization (m\u00e1s bien su ausencia) en Python.</p> <p>Pero pens\u00e9: \"mejor explico qu\u00e9 es Tail Call Optimization antes, que si no no se entiende...\"</p> <p>\"Ah, pero no puedo explicar qu\u00e9 es Tail Call Optimization sin antes explicar qu\u00e9 son las Tail Calls...\"</p> <p>\"Ah! pero entonces, deber\u00eda explicar...\" Y mi cabeza explot\u00f3.</p> <p>\"RecursionError: maximum recursion depth exceeded\".</p> <p>En esta charla primero revisitaremos - con condici\u00f3n de parada, \u00a1lo prometo! - el concepto de recursividad, sus tipos, la guerra \"iterativo vs recursivo\", c\u00f3mo Python \"guarda\" el estado de las funciones en el call stack... para finalmente entender qu\u00e9 es el famoso Tail Call Optimization y por qu\u00e9 nuestro querid\u00edsimo Guido no quiso implementarlo en Python.</p> <p>----------------------------------------------------------------------------------------------------</p> <p>Ponente: Javier Luna. Llevo siendo ingeniero desde que tengo uso de raz\u00f3n, aunque empec\u00e9 a crear software a los 8 a\u00f1os.<br/>Soy una persona inquieta, curiosa y autodidacta y eso se ve muy reflejado en mi carrera profesional: He sido investigador, desarrollador backend, data engineer, lead teacher en un bootcamp de data science... De tanto so\u00f1ar despierto he acabado trabajando en la nube, literalmente. Soy SDE en Amazon Web Services en Berl\u00edn.</p> ", "venue_country": "", "event_id": 277663457, "fee_desc": "", "chapter_id": 13310742, "venue_lat": -8.521147, "meetupId": "python-madrid"}, {"is_private": "false", "venue_name": "Online event", "rsvp_limit": 30, "fee_currency": "USD", "fee": 0, "venue_lon": 179.1962, "title": "Get rid of Matlab! (struggling process from Matlab to Python) ", "type": "Meetup", "venue_address1": "", "venue_address2": "", "local_time": "2021-04-27 19:00:00 EDT", "fee_label": "", "myRsvp": -1, "ctime": "2021-04-19 04:02:02 EDT", "guest_limit": 0, "rsvp_closed": "false", "confirmCount": 6, "venue_id": 26906060, "venue_zip": "", "chapter_url": "https://www.meetup.com/PyLadies-BCN/#", "servertime": "2021-04-27 13:00:00 EDT", "venue_city": "", "event_url": "https://www.meetup.com/PyLadies-BCN/events/277660064/", "allow_maybe_rsvps": "false", "commentCount": 0, "descr": "<p>After a long mental process I decided to switch from Matlab to Python to process my data. First, I had to decide the platform (IDLE, Spyder, Jupyter Notebook) and I chose one, but I changed after some time.</p> <p>Then, I started by trying to open a txt file and I spend one entire month to do so (I did not know about the libraries). After all, I am glad I took this decision, but there are still many things to learn yet. Pyhton community is lovelly and there is many work already done.</p> <p>The session would consist on explaining my struggling process and exchange ideas on how to optimize it for someone else.</p> <p>Speaker: Anna Mujal-Colilles<br/>Level: Beginner<br/>Language: English/Spanish</p> ", "venue_country": "", "event_id": 277660064, "fee_desc": "", "chapter_id": 12994802, "venue_lat": -8.521147, "meetupId": "PyLadies-BCN"}, {"is_private": "false", "venue_name": "Online event", "rsvp_limit": 0, "fee_currency": "USD", "fee": 0, "venue_lon": 179.1962, "title": "MeetUp Python Alicante", "type": "Meetup", "venue_address1": "", "venue_address2": "", "local_time": "2021-04-29 19:00:00 EDT", "fee_label": "", "myRsvp": -1, "ctime": "2021-04-23 12:46:15 EDT", "guest_limit": 0, "rsvp_closed": "false", "confirmCount": 2, "venue_id": 26906060, "venue_zip": "", "chapter_url": "https://www.meetup.com/python_alc/#", "servertime": "2021-04-29 13:00:00 EDT", "venue_city": "", "event_url": "https://www.meetup.com/python_alc/events/277756781/", "allow_maybe_rsvps": "false", "commentCount": 0, "descr": "<p>\u00a1 MeetUp Python Alicante !</p> <p>O lo que es lo mismo, una quedada informal d\u00f3nde hablaremos sobre Python, nuestros proyectos en los que estamos trabajando tanto de forma profesional como por afici\u00f3n.</p> <p>Al ser un evento informal, no hace falta que tengas ning\u00fan conocimiento previo, solo inter\u00e9s por la programaci\u00f3n en general y en Python en particular; as\u00ed que es una buena oportunidad si quieres empezar.</p> <p>\u2022 Qu\u00e9 has de traer<br/>Ganas de participar y hacer comunidad.</p> <p>El evento va a ser a trav\u00e9s de nuestro Discord. Cuando te apuntes al evento podr\u00e1s ver el enlace para unirte.</p> ", "venue_country": "", "event_id": 277756781, "fee_desc": "", "chapter_id": 26484481, "venue_lat": -8.521147, "meetupId": "python_alc"}]